{"name":"展览","postlist":[{"title":"看展：2021成都双年展","slug":null,"date":"2022-05-08T14:16:31.000Z","updated":"2022-05-08T14:36:34.455Z","comments":null,"path":"api/articles/看展：2021成都双年展.json","excerpt":null,"keywords":null,"cover":"/kewenlu/images/202205081.jpg","content":null,"raw":null,"categories":[{"name":"人文","path":"api/categories/人文.json"}],"tags":[{"name":"人文","path":"api/tags/人文.json"},{"name":"展览","path":"api/tags/展览.json"}]},{"title":"看展：成都画院，隐秘的日常","slug":null,"date":"2022-04-30T13:29:12.000Z","updated":"2022-04-30T14:05:12.445Z","comments":null,"path":"api/articles/看展：成都画院，隐秘的日常.json","excerpt":null,"keywords":null,"cover":"/kewenlu/images/2022/202204301.jpg","content":null,"raw":null,"categories":[{"name":"人文","path":"api/categories/人文.json"}],"tags":[{"name":"人文","path":"api/tags/人文.json"},{"name":"展览","path":"api/tags/展览.json"}]}]}