{"name":"编译器","postlist":[{"title":"LLVM的Intrinsics函数及其实现","slug":null,"date":"2022-03-31T14:49:59.000Z","updated":"2022-03-31T14:51:56.364Z","comments":null,"path":"api/articles/LLVM的Intrinsics函数及其实现.json","excerpt":null,"keywords":null,"cover":null,"content":null,"raw":null,"categories":[{"name":"科技","path":"api/categories/科技.json"}],"tags":[{"name":"科技","path":"api/tags/科技.json"},{"name":"编译器","path":"api/tags/编译器.json"}]},{"title":"MLIR:编译器基础架构重定义","slug":null,"date":"2022-04-01T12:48:23.000Z","updated":"2022-04-01T14:38:27.980Z","comments":null,"path":"api/articles/MLIR-编译器基础架构重定义.json","excerpt":null,"keywords":null,"cover":"/kewenlu/images/2022/202204011.jpg","content":null,"raw":null,"categories":[{"name":"科技","path":"api/categories/科技.json"}],"tags":[{"name":"科技","path":"api/tags/科技.json"},{"name":"编译器","path":"api/tags/编译器.json"}]}]}